dockerdb/__init__.py
dockerdb/influxdb.py
dockerdb/influxdb_pytest.py
dockerdb/mongo.py
dockerdb/mongo_pytest.py
dockerdb/service.py
dockerdb-0.6.1.dist-info/LICENSE
dockerdb-0.6.1.dist-info/METADATA
dockerdb-0.6.1.dist-info/WHEEL
dockerdb-0.6.1.dist-info/top_level.txt
dockerdb-0.6.1.dist-info/RECORD
